[{"name":"userId","value":"402276","domain":".betting.co.zw","path":"/","expires":1735114654,"size":12,"httpOnly":false,"secure":true,"session":false,"sameSite":"None","priority":"Medium","sameParty":false,"sourceScheme":"Secure"},{"name":"uId","value":"Q","domain":".betting.co.zw","path":"/","expires":1735114654,"size":4,"httpOnly":false,"secure":true,"session":false,"sameSite":"None","priority":"Medium","sameParty":false,"sourceScheme":"Secure"},{"name":"at","value":"MwYwLAhgjBBMAMBaARrZATRYBsBTWiAHMtgJyKwQgCsYy8u6ppsQA","domain":".betting.co.zw","path":"/","expires":1735114653,"size":55,"httpOnly":false,"secure":true,"session":false,"sameSite":"None","priority":"Medium","sameParty":false,"sourceScheme":"Secure"},{"name":"__cf_bm","value":"eo2U8AeBVU6rpt4sTxqnxAUDobbv8ulDmNmpnLs5mJQ-1732522656-1.0.1.1-vL7ykCWM.3qZmfpSnPI0YkYJvjU8UsaujQpSQkA7rsYElSLh.9rm56GnlQFMmwCFkjmMyou8Uy8bnyt08KHV8Q","domain":".betting.co.zw","path":"/","expires":1732524454.091633,"size":156,"httpOnly":true,"secure":true,"session":false,"sameSite":"None","priority":"Medium","sameParty":false,"sourceScheme":"Secure"},{"name":"_cfuvid","value":"ooP2vzhZg28uW4EMeCN4u.eXhS10xxkKmqnm3CCrjSI-1732522656169-0.0.1.1-604800000","domain":".betting.co.zw","path":"/","expires":-1,"size":82,"httpOnly":true,"secure":true,"session":true,"sameSite":"None","priority":"Medium","sameParty":false,"sourceScheme":"Secure"},{"name":"_ga_9TWXQVPY3G","value":"GS1.1.1732522651.1.1.1732522653.0.0.0","domain":".betting.co.zw","path":"/","expires":1767082653.12072,"size":51,"httpOnly":false,"secure":false,"session":false,"priority":"Medium","sameParty":false,"sourceScheme":"Secure"},{"name":"_ga","value":"GA1.1.1850775254.1732522651","domain":".betting.co.zw","path":"/","expires":1767082651.348521,"size":30,"httpOnly":false,"secure":false,"session":false,"priority":"Medium","sameParty":false,"sourceScheme":"Secure"}]